metavino/__init__.py
metavino/app/__init__.py
metavino/app/instance_segment_vino.py
metavino/app/object_classification_vino.py
metavino/app/object_detection_vino.py
metavino/app/onnx_to_vino.py
metavino/app/saliency_segment_vino.py
metavino/app/yolo_segment_vino.py
metavino/model_zoo/__init__.py
metavino/utils/__init__.py
metavino/utils/general.py
meta_vino-3.6.21.dist-info/METADATA
meta_vino-3.6.21.dist-info/WHEEL
meta_vino-3.6.21.dist-info/top_level.txt
meta_vino-3.6.21.dist-info/zip-safe
meta_vino-3.6.21.dist-info/RECORD
