Metadata-Version: 2.1
Name: meta-vino
Version: 3.6.21
Summary: Meta Vino Toolkit
Home-page: https://github.com/CachCheng/cvopenvino
Author: CachCheng
Author-email: tkggpdc2007@163.com
License: Apache-2.0
Requires-Dist: opencv-python
Requires-Dist: setuptools
Requires-Dist: openvino
Requires-Dist: numpy
Requires-Dist: pillow
